{
  "urn": {
    "tags": {
      "op": "analyze_image",
      "type": "vision",
      "model_type": "mlx",
      "in": "media:png;binary",
      "out": "media:vision-inference-output;textable;keyed"
    }
  },
  "command": "analyze_image",
  "title": "Analyze Image with Vision Model (MLX)",
  "cap_description": "Analyze images using MLX-based vision-language models on Apple Silicon",
  "metadata": {},
  "media_specs": {
    "media:vision-inference-output;textable;keyed": {
      "media_type": "application/json",
      "profile_uri": "https://capns.org/schema/vision_inference-output",
      "schema": {
        "type": "object",
        "additionalProperties": false,
        "required": [
          "success",
          "description",
          "model_name",
          "image_path"
        ],
        "properties": {
          "success": {
            "type": "boolean",
            "description": "Whether the image analysis succeeded"
          },
          "description": {
            "type": "string",
            "description": "Generated description/analysis of the image"
          },
          "model_name": {
            "type": "string",
            "minLength": 1,
            "description": "Name of the vision model used"
          },
          "image_path": {
            "type": "string",
            "description": "Path to the analyzed image"
          },
          "generation_time_ms": {
            "type": "number",
            "minimum": 0,
            "description": "Analysis time in milliseconds"
          },
          "tokens_generated": {
            "type": "integer",
            "minimum": 0,
            "description": "Number of tokens generated"
          }
        }
      }
    }
  },
  "args": [
    {
      "media_urn": "media:mlx-model-path;textable;scalar",
      "required": true,
      "sources": [
        {
          "cli_flag": "--model"
        },
        {
          "position": 0
        }
      ],
      "arg_description": "Path to MLX vision model directory",
      "validation": {
        "min_length": 1
      }
    },
    {
      "media_urn": "media:image-path;textable;scalar",
      "required": true,
      "sources": [
        {
          "cli_flag": "--image"
        },
        {
          "position": 1
        }
      ],
      "arg_description": "Path to the image file to analyze (local path or HTTP(S) URL)",
      "validation": {
        "min_length": 1
      }
    },
    {
      "media_urn": "media:prompt-text;textable;scalar",
      "required": false,
      "sources": [
        {
          "cli_flag": "--prompt"
        }
      ],
      "arg_description": "Text prompt for the image analysis",
      "validation": {
        "min_length": 1,
        "max_length": 4096
      },
      "default_value": "Describe this image in detail."
    },
    {
      "media_urn": "media:max-tokens;textable;numeric;scalar",
      "required": false,
      "sources": [
        {
          "cli_flag": "--max-tokens"
        }
      ],
      "arg_description": "Maximum number of tokens to generate",
      "validation": {
        "min": 1,
        "max": 4096
      },
      "default_value": 256
    }
  ],
  "output": {
    "media_urn": "media:vision-inference-output;textable;keyed",
    "output_description": "Image analysis with description and metadata"
  }
}